aya/__init__.py
snapshotserengeti_aya-0.2.dist-info/DESCRIPTION.rst
snapshotserengeti_aya-0.2.dist-info/METADATA
snapshotserengeti_aya-0.2.dist-info/RECORD
snapshotserengeti_aya-0.2.dist-info/WHEEL
snapshotserengeti_aya-0.2.dist-info/metadata.json
snapshotserengeti_aya-0.2.dist-info/top_level.txt
